gerrychain/__init__.py
gerrychain/_version.py
gerrychain/accept.py
gerrychain/chain.py
gerrychain/grid.py
gerrychain/metagraph.py
gerrychain/tree.py
gerrychain/constraints/__init__.py
gerrychain/constraints/bounds.py
gerrychain/constraints/compactness.py
gerrychain/constraints/contiguity.py
gerrychain/constraints/validity.py
gerrychain/graph/__init__.py
gerrychain/graph/adjacency.py
gerrychain/graph/geo.py
gerrychain/graph/graph.py
gerrychain/meta/__init__.py
gerrychain/meta/diversity.py
gerrychain/metrics/__init__.py
gerrychain/metrics/compactness.py
gerrychain/metrics/partisan.py
gerrychain/optimization/__init__.py
gerrychain/optimization/gingleator.py
gerrychain/optimization/optimization.py
gerrychain/partition/__init__.py
gerrychain/partition/assignment.py
gerrychain/partition/geographic.py
gerrychain/partition/partition.py
gerrychain/partition/subgraphs.py
gerrychain/proposals/__init__.py
gerrychain/proposals/proposals.py
gerrychain/proposals/spectral_proposals.py
gerrychain/proposals/tree_proposals.py
gerrychain/updaters/__init__.py
gerrychain/updaters/compactness.py
gerrychain/updaters/county_splits.py
gerrychain/updaters/cut_edges.py
gerrychain/updaters/election.py
gerrychain/updaters/flows.py
gerrychain/updaters/locality_split_scores.py
gerrychain/updaters/spanning_trees.py
gerrychain/updaters/tally.py
gerrychain/vendor/__init__.py
gerrychain/vendor/utm/__init__.py
gerrychain/vendor/utm/conversion.py
gerrychain/vendor/utm/error.py
gerrychain-0.3.2.dist-info/LICENSE
gerrychain-0.3.2.dist-info/METADATA
gerrychain-0.3.2.dist-info/WHEEL
gerrychain-0.3.2.dist-info/top_level.txt
gerrychain-0.3.2.dist-info/RECORD
