Metadata-Version: 2.1
Name: gerrychain
Version: 0.3.2
Summary: Use Markov chain Monte Carlo to analyze districting plans and gerrymanders
Home-page: https://github.com/mggg/GerryChain
Author: Metric Geometry and Gerrymandering Group
Author-email: engineering@mggg.org
Maintainer: Metric Geometry and Gerrymandering Group
Maintainer-email: engineering@mggg.org
Keywords: GerryChain
Classifier: Programming Language :: Python :: 3.9
Classifier: Programming Language :: Python :: 3.10
Classifier: Programming Language :: Python :: 3.11
Classifier: Programming Language :: Python :: 3.12
Classifier: Operating System :: OS Independent
Classifier: License :: OSI Approved :: BSD License
Provides-Extra: geo
License-File: LICENSE
